git_time_tracking/__about__.py
git_time_tracking/__init__.py
git_time_tracking/__main__.py
git_time_tracking/utils.py
git_time_tracking-0.0.2.dist-info/METADATA
git_time_tracking-0.0.2.dist-info/WHEEL
git_time_tracking-0.0.2.dist-info/entry_points.txt
git_time_tracking-0.0.2.dist-info/licenses/LICENSE
git_time_tracking-0.0.2.dist-info/RECORD
